nsoenv/__init__.py
nsoenv-0.0.1.dist-info/LICENSE
nsoenv-0.0.1.dist-info/METADATA
nsoenv-0.0.1.dist-info/WHEEL
nsoenv-0.0.1.dist-info/top_level.txt
nsoenv-0.0.1.dist-info/RECORD
