Metadata-Version: 2.1
Name: nsoenv
Version: 0.0.1
Summary: nsoenv lets you easily switch between multiple versions of NSO - Network Service Orchestrator. It's simple, unobtrusive, and follows the UNIX tradition of single-purpose tools that do one thing well.
Home-page: https://github.com/kirankotari/nsoenv.git
Author: Kiran Kumar Kotari
Author-email: kirankotari@live.com
License: UNKNOWN
Keywords: Network Service Orchestrator Envrinoments,multiple versions of NSO
Platform: UNKNOWN
Classifier: Development Status :: 3 - Alpha
Classifier: Intended Audience :: Developers
Classifier: Topic :: Software Development :: Build Tools
Classifier: License :: OSI Approved :: MIT License
Classifier: Operating System :: Microsoft :: Windows
Classifier: Programming Language :: Python :: 2.6
Classifier: Programming Language :: Python :: 2.7
Classifier: Programming Language :: Python :: 3.1
Classifier: Programming Language :: Python :: 3.2
Classifier: Programming Language :: Python :: 3.3
Classifier: Programming Language :: Python :: 3.4
Classifier: Programming Language :: Python :: 3.5
Classifier: Programming Language :: Python :: 3.6
Classifier: Programming Language :: Python :: 3.7
